{"cameraMode":{"drawMode":0,"name":"Shaded","section":"Shading Mode"},"sceneLighting":true,"audioPlay":false,"sceneViewState":{"m_AlwaysRefresh":false,"showFog":true,"showSkybox":true,"showFlares":true,"showImageEffects":true,"showParticleSystems":true,"showVisualEffectGraphs":true,"m_FxEnabled":true},"in2DMode":false,"pivot":{"x":2.832826614379883,"y":7.262568473815918,"z":-0.5551683902740479},"rotation":{"x":0.312626451253891,"y":-0.4135357737541199,"z":0.1536756306886673,"w":0.8412317633628845},"size":2.918032169342041,"orthographic":true}